i2s_ecg/__init__.py
i2s_ecg/app.py
i2s_ecg/ecg.py
i2s_ecg/run.py
i2s_ecg/data/Heart_Disease_Prediction_using_ECG.pkl
i2s_ecg/data/PCA_ECG.pkl
i2s_ecg-0.1.10.dist-info/METADATA
i2s_ecg-0.1.10.dist-info/WHEEL
i2s_ecg-0.1.10.dist-info/top_level.txt
i2s_ecg-0.1.10.dist-info/RECORD
