Metadata-Version: 2.1
Name: i2s-ecg
Version: 0.1.10
Summary: the package for ECG signal processing
Home-page: https://github.com/xzxg001/i2s_ecg
Author: zou linzhuang
Author-email: zoulinzhuang2204@hnu.edu.cn
License: MIT License
Classifier: Programming Language :: Python :: 3
Classifier: License :: OSI Approved :: MIT License
Classifier: Operating System :: OS Independent
Requires-Dist: scikit-learn ==1.2.2
Requires-Dist: scikit-image
Requires-Dist: unzip
Requires-Dist: joblib
Requires-Dist: pandas
Requires-Dist: matplotlib
Requires-Dist: natsort
Requires-Dist: streamlit ==1.37.0
Requires-Dist: streamlit-cropper
Requires-Dist: scipy
Requires-Dist: numpy ==1.25.2
Requires-Dist: pillow
